harmony_auth/__init__.py
harmony_auth/harmony.py
harmony_auth/models.py
harmony_auth-0.1.5.dist-info/WHEEL
harmony_auth-0.1.5.dist-info/METADATA
harmony_auth-0.1.5.dist-info/RECORD
