Metadata-Version: 2.1
Name: harmony-auth
Version: 0.1.5
Summary: Discord OAuth2 Implicit Grant Dependency for FastAPI
Home-page: https://github.com/williamhatcher/harmonyAuth
License: MIT
Author: William Hatcher
Author-email: william@hatcher.work
Requires-Python: >=3.9,<4.0
Classifier: License :: OSI Approved :: MIT License
Classifier: Programming Language :: Python :: 3
Classifier: Programming Language :: Python :: 3.9
Classifier: Programming Language :: Python :: 3.10
Requires-Dist: fastapi (>=0.79.0,<0.80.0)
Requires-Dist: httpx (>=0.23.0,<0.24.0)
Requires-Dist: python-dateutil (>=2.8.2,<3.0.0)
Requires-Dist: redis[hiredis] (>=4.3.4,<5.0.0)
Requires-Dist: uvicorn (>=0.18.2,<0.19.0)
Project-URL: Repository, https://github.com/williamhatcher/harmonyAuth
